opentok/__init__.py
opentok/archives.py
opentok/broadcast.py
opentok/captions.py
opentok/endpoints.py
opentok/exceptions.py
opentok/opentok.py
opentok/render.py
opentok/session.py
opentok/sip_call.py
opentok/stream.py
opentok/streamlist.py
opentok/version.py
opentok/websocket_audio_connection.py
opentok-3.13.0.dist-info/LICENSE.txt
opentok-3.13.0.dist-info/METADATA
opentok-3.13.0.dist-info/WHEEL
opentok-3.13.0.dist-info/top_level.txt
opentok-3.13.0.dist-info/RECORD
