Metadata-Version: 2.1
Name: opentok
Version: 3.13.0
Summary: OpenTok server-side SDK
Home-page: https://github.com/opentok/Opentok-Python-SDK/
Author: TokBox, Inc.
Author-email: support@tokbox.com
License: LICENSE.txt
Keywords: video chat tokbox tok opentok python media webrtc archiving realtime
Classifier: Development Status :: 5 - Production/Stable
Classifier: Intended Audience :: Developers
Classifier: Intended Audience :: Telecommunications Industry
Classifier: License :: OSI Approved :: MIT License
Classifier: Programming Language :: Python :: 3
Classifier: Programming Language :: Python :: 3.9
Classifier: Programming Language :: Python :: 3.10
Classifier: Programming Language :: Python :: 3.11
Classifier: Programming Language :: Python :: 3.12
Classifier: Programming Language :: Python :: 3.13
Classifier: Topic :: Communications
Classifier: Topic :: Communications :: Chat
Classifier: Topic :: Communications :: Conferencing
Classifier: Topic :: Multimedia :: Video :: Capture
Classifier: Topic :: Multimedia :: Video :: Display
Classifier: Topic :: Multimedia :: Sound/Audio :: Players
Classifier: Topic :: Multimedia :: Sound/Audio :: Capture/Recording
Classifier: Topic :: Software Development :: Libraries :: Python Modules
License-File: LICENSE.txt
